nxcli/__init__.py
nxcli/app.py
nxcli/cli.py
nxcli/exceptions.py
nxcli/nxcli.py
nxcli/commands/__init__.py
nxcli/commands/config.py
nxcli/commands/git.py
nxcli/commands/install.py
nxcli/commands/make.py
nxcli/commands/setup.py
nxcli/commands/update.py
nxcli/commands/utils.py
nxcli/config/__init__.py
nxcli/config/common_site_config.py
nxcli/config/lets_encrypt.py
nxcli/config/nginx.py
nxcli/config/procfile.py
nxcli/config/production_setup.py
nxcli/config/redis.py
nxcli/config/site_config.py
nxcli/config/supervisor.py
nxcli/config/systemd.py
nxcli/config/templates/502.html
nxcli/config/templates/Procfile
nxcli/config/templates/letsencrypt.cfg
nxcli/config/templates/nginx.conf
nxcli/config/templates/nginx_default.conf
nxcli/config/templates/nxcli_manager_nginx.conf
nxcli/config/templates/nxenv_sudoers
nxcli/config/templates/redis_cache.conf
nxcli/config/templates/redis_queue.conf
nxcli/config/templates/supervisor.conf
nxcli/config/templates/systemd/nxenv-nxcli-node-socketio.service
nxcli/config/templates/systemd/nxenv-nxcli-nxenv-default-worker.service
nxcli/config/templates/systemd/nxenv-nxcli-nxenv-long-worker.service
nxcli/config/templates/systemd/nxenv-nxcli-nxenv-schedule.service
nxcli/config/templates/systemd/nxenv-nxcli-nxenv-short-worker.service
nxcli/config/templates/systemd/nxenv-nxcli-nxenv-web.service
nxcli/config/templates/systemd/nxenv-nxcli-redis-cache.service
nxcli/config/templates/systemd/nxenv-nxcli-redis-queue.service
nxcli/config/templates/systemd/nxenv-nxcli-redis.target
nxcli/config/templates/systemd/nxenv-nxcli-web.target
nxcli/config/templates/systemd/nxenv-nxcli-workers.target
nxcli/config/templates/systemd/nxenv-nxcli.target
nxcli/patches/__init__.py
nxcli/patches/patches.txt
nxcli/patches/v5/__init__.py
nxcli/patches/v5/fix_backup_cronjob.py
nxcli/patches/v5/fix_user_permissions.py
nxcli/patches/v5/set_live_reload_config.py
nxcli/patches/v5/update_archived_sites.py
nxcli/playbooks/README.md
nxcli/playbooks/create_user.yml
nxenv_nxcli-5.0.0.dev0.dist-info/METADATA
nxenv_nxcli-5.0.0.dev0.dist-info/WHEEL
nxenv_nxcli-5.0.0.dev0.dist-info/entry_points.txt
nxenv_nxcli-5.0.0.dev0.dist-info/licenses/LICENSE
nxenv_nxcli-5.0.0.dev0.dist-info/RECORD
