Metadata-Version: 2.1
Name: nxenv-nxcli
Version: 5.0.0.dev0
Summary: CLI to manage Multi-tenant deployments for Nxenv apps
Project-URL: Changelog, https://github.com/nxenv/nxcli/releases
Project-URL: Documentation, https://nxenvframework.com/docs/user/en/nxcli
Project-URL: Homepage, https://nxenv.io/nxcli
Project-URL: Source, https://github.com/nxenv/nxcli
Author-email: "KhulnaSoft, Ltd" <info@khulnasoft.com>
License: GPL-3.0-only
License-File: LICENSE
Classifier: Development Status :: 5 - Production/Stable
Classifier: Environment :: Console
Classifier: License :: OSI Approved :: GNU General Public License v3 (GPLv3)
Classifier: Natural Language :: English
Classifier: Operating System :: MacOS
Classifier: Operating System :: OS Independent
Classifier: Topic :: Software Development :: Build Tools
Classifier: Topic :: Software Development :: User Interfaces
Classifier: Topic :: System :: Installation/Setup
Requires-Python: >=3.8
Requires-Dist: click>=7.0
Requires-Dist: gitpython~=3.1.30
Requires-Dist: honcho
